openzeppelin/__init__.py
openzeppelin/access/ownable.cairo
openzeppelin/account/Account.cairo
openzeppelin/account/AddressRegistry.cairo
openzeppelin/account/IAccount.cairo
openzeppelin/account/library.cairo
openzeppelin/introspection/ERC165.cairo
openzeppelin/introspection/IERC165.cairo
openzeppelin/security/initializable.cairo
openzeppelin/security/pausable.cairo
openzeppelin/security/safemath.cairo
openzeppelin/token/erc20/ERC20.cairo
openzeppelin/token/erc20/ERC20_Mintable.cairo
openzeppelin/token/erc20/ERC20_Pausable.cairo
openzeppelin/token/erc20/ERC20_Upgradeable.cairo
openzeppelin/token/erc20/library.cairo
openzeppelin/token/erc20/interfaces/IERC20.cairo
openzeppelin/token/erc721/ERC721_Mintable_Burnable.cairo
openzeppelin/token/erc721/ERC721_Mintable_Pausable.cairo
openzeppelin/token/erc721/library.cairo
openzeppelin/token/erc721/interfaces/IERC721.cairo
openzeppelin/token/erc721/interfaces/IERC721_Metadata.cairo
openzeppelin/token/erc721/interfaces/IERC721_Receiver.cairo
openzeppelin/token/erc721/utils/ERC721_Holder.cairo
openzeppelin/token/erc721_enumerable/ERC721_Enumerable_Mintable_Burnable.cairo
openzeppelin/token/erc721_enumerable/library.cairo
openzeppelin/token/erc721_enumerable/interfaces/IERC721_Enumerable.cairo
openzeppelin/upgrades/Proxy.cairo
openzeppelin/upgrades/library.cairo
openzeppelin/utils/constants.cairo
openzeppelin_cairo_contracts_test-0.1.0.dist-info/LICENSE
openzeppelin_cairo_contracts_test-0.1.0.dist-info/METADATA
openzeppelin_cairo_contracts_test-0.1.0.dist-info/WHEEL
openzeppelin_cairo_contracts_test-0.1.0.dist-info/top_level.txt
openzeppelin_cairo_contracts_test-0.1.0.dist-info/RECORD
