Metadata-Version: 2.1
Name: openzeppelin-cairo-contracts-test
Version: 0.1.0
Summary: Library for secure smart contract development written in Cairo
Home-page: https://github.com/OpenZeppelin/cairo-contracts
Author: OpenZeppelin Community
Author-email: maintainers@openzeppelin.org
License: MIT
Platform: any
Classifier: Operating System :: OS Independent
License-File: LICENSE
Requires-Dist: importlib-metadata (>=4.0)
Provides-Extra: testing
Requires-Dist: setuptools ; extra == 'testing'
Requires-Dist: tox ; extra == 'testing'
Requires-Dist: pytest ; extra == 'testing'
